Metadata-Version: 2.1
Name: helloworldah
Version: 0.0.1
Summary: prints hello world
Home-page: 
Author: Ashim Khanal
Author-email: ashimkhanal18@gmail.com 
License: MIT
Keywords: printhelloworld
Platform: UNKNOWN
Classifier: Development Status :: 5 - Production/Stable
Classifier: Intended Audience :: Education
Classifier: Operating System :: Microsoft :: Windows :: Windows 10
Classifier: License :: OSI Approved :: MIT License
Classifier: Programming Language :: Python :: 3
License-File: LICENSE.txt
